napari_large_image_importer/__init__.py
napari_large_image_importer/_widget.py
napari_large_image_importer/napari.yaml
napari_large_image_importer/_tests/__init__.py
napari_large_image_importer/_tests/test_widget.py
napari_large_image_importer-0.0.3.dist-info/licenses/LICENSE
napari_large_image_importer-0.0.3.dist-info/METADATA
napari_large_image_importer-0.0.3.dist-info/WHEEL
napari_large_image_importer-0.0.3.dist-info/entry_points.txt
napari_large_image_importer-0.0.3.dist-info/top_level.txt
napari_large_image_importer-0.0.3.dist-info/RECORD
