Metadata-Version: 2.4
Name: napari-large-image-importer
Version: 0.0.3
Summary: Napari plugin for easy, memory-efficient import of large images.
Home-page: https://github.com/hiroalchem/napari-large-image-importer
Author: Hiroki Kawai
Author-email: h.kawai888@gmail.com
License: BSD-3-Clause
Project-URL: Bug Tracker, https://github.com/hiroalchem/napari-large-image-importer/issues
Project-URL: Documentation, https://github.com/hiroalchem/napari-large-image-importer#README.md
Project-URL: Source Code, https://github.com/hiroalchem/napari-large-image-importer
Project-URL: User Support, https://github.com/hiroalchem/napari-large-image-importer/issues
Classifier: Development Status :: 2 - Pre-Alpha
Classifier: Framework :: napari
Classifier: Intended Audience :: Developers
Classifier: License :: OSI Approved :: BSD License
Classifier: Operating System :: OS Independent
Classifier: Programming Language :: Python
Classifier: Programming Language :: Python :: 3
Classifier: Programming Language :: Python :: 3 :: Only
Classifier: Programming Language :: Python :: 3.8
Classifier: Programming Language :: Python :: 3.9
Classifier: Programming Language :: Python :: 3.10
Classifier: Topic :: Scientific/Engineering :: Image Processing
Requires-Python: >=3.8
License-File: LICENSE
Requires-Dist: numpy
Requires-Dist: magicgui
Requires-Dist: qtpy
Requires-Dist: tifffile
Requires-Dist: zarr
Requires-Dist: dask
Provides-Extra: testing
Requires-Dist: tox; extra == "testing"
Requires-Dist: pytest; extra == "testing"
Requires-Dist: pytest-cov; extra == "testing"
Requires-Dist: pytest-qt; extra == "testing"
Requires-Dist: napari; extra == "testing"
Requires-Dist: pyqt5; extra == "testing"
Dynamic: license-file
